appfly/__init__.py
appfly/server.py
appfly/app/__init__.py
appfly/app/response.py
appfly/app/routes/__init__.py
appfly/app/routes/ping.py
appfly-2.1.0.dist-info/LICENSE
appfly-2.1.0.dist-info/METADATA
appfly-2.1.0.dist-info/WHEEL
appfly-2.1.0.dist-info/top_level.txt
appfly-2.1.0.dist-info/RECORD
