Metadata-Version: 2.1
Name: appfly
Version: 2.1.0
Summary: This pkg encapsulate the base flask server configurations
Home-page: https://github.com/italojs/appfly
Author: Italo José G. de Oliveira
Author-email: italo.i@live.com
License: MIT license
Keywords: appfly
Platform: UNKNOWN
Classifier: Intended Audience :: Developers
Classifier: License :: OSI Approved :: MIT License
Classifier: Natural Language :: English
Classifier: Programming Language :: Python :: 3.4
Classifier: Programming Language :: Python :: 3.5
Classifier: Programming Language :: Python :: 3.6
Classifier: Programming Language :: Python :: 3.7
Requires-Dist: Flask (==1.0.2)
Requires-Dist: flask-cors (==3.0.6)
Requires-Dist: Flask-SocketIO (==3.0.2)
Requires-Dist: jsonmerge (==1.5.2)
